poetry_request_spoofing_plugin/__init__.py
poetry_request_spoofing_plugin/plugin.py
poetry_request_spoofing_plugin-1.0.1.dist-info/entry_points.txt
poetry_request_spoofing_plugin-1.0.1.dist-info/METADATA
poetry_request_spoofing_plugin-1.0.1.dist-info/WHEEL
poetry_request_spoofing_plugin-1.0.1.dist-info/RECORD
